rhotrix/__init__.py
rhotrix/hrotrix.py
rhotrix-0.1.0.dist-info/LICENCE.TXT
rhotrix-0.1.0.dist-info/METADATA
rhotrix-0.1.0.dist-info/WHEEL
rhotrix-0.1.0.dist-info/top_level.txt
rhotrix-0.1.0.dist-info/RECORD
