Metadata-Version: 2.1
Name: rhotrix
Version: 0.1.0
Summary: A Python library to implement and manipulate Rhotrix matrices.
Home-page: https://github.com/giulicrenna/rhotrix
Author: Giuliano Crenna
Author-email: giulicrenna@gmail.com
Classifier: Programming Language :: Python :: 3
Classifier: License :: OSI Approved :: MIT License
Classifier: Operating System :: OS Independent
Requires-Python: >=3.6
License-File: LICENCE.TXT
